aici/__init__.py
aici/__main__.py
aici/i18n.py
aici/main.py
aici/mock_api.py
aici/version.py
aici-0.1.2.dist-info/licenses/LICENSE
e2e/__init__.py
e2e/conftest.py
e2e/mock_openai.py
e2e/run_with_mock.py
e2e/test_clipboard.py
e2e/test_e2e.py
e2e/test_e2e_mocked.py
aici-0.1.2.dist-info/METADATA
aici-0.1.2.dist-info/WHEEL
aici-0.1.2.dist-info/entry_points.txt
aici-0.1.2.dist-info/top_level.txt
aici-0.1.2.dist-info/RECORD
